gobbezlearningtoolbox/__init__.py
gobbezlearningtoolbox/cookiecutter.py
gobbezlearningtoolbox/core.py
gobbezlearningtoolbox/createpypimodule.py
gobbezlearningtoolbox/datascience.py
gobbezlearningtoolbox/deeplearning.py
gobbezlearningtoolbox/django.py
gobbezlearningtoolbox/listall.py
gobbezlearningtoolbox/ollama.py
gobbezlearningtoolbox/print_fonts.py
gobbezlearningtoolbox/telegrambot.py
gobbezlearningtoolbox-0.5.0.dist-info/LICENSE
gobbezlearningtoolbox-0.5.0.dist-info/METADATA
gobbezlearningtoolbox-0.5.0.dist-info/WHEEL
gobbezlearningtoolbox-0.5.0.dist-info/top_level.txt
gobbezlearningtoolbox-0.5.0.dist-info/RECORD
