Metadata-Version: 2.1
Name: gobbezlearningtoolbox
Version: 0.5.0
Summary: My learning toolbox, with every code that i have studied
Home-page: https://github.com/gobbez/learningtoolbox
Author: Andrea Gobbetti
Author-email: a.gobbez@hotmail.it
Classifier: Programming Language :: Python :: 3
Classifier: License :: OSI Approved :: MIT License
Classifier: Operating System :: OS Independent
Requires-Python: >=3.6
License-File: LICENSE
